ksuid/__init__.py
ksuid/cli.py
ksuid/prefixed_examples.py
ksuid_python-1.0.0.dist-info/METADATA
ksuid_python-1.0.0.dist-info/WHEEL
ksuid_python-1.0.0.dist-info/entry_points.txt
ksuid_python-1.0.0.dist-info/licenses/LICENSE
ksuid_python-1.0.0.dist-info/RECORD
