Metadata-Version: 2.4
Name: ksuid-python
Version: 1.0.0
Summary: K-Sortable Unique Identifier (KSUID) implementation for Python 3.13+
Project-URL: Homepage, https://github.com/geneseas/ksuid-python
Project-URL: Documentation, https://github.com/geneseas/ksuid-python/blob/main/README.md
Project-URL: Repository, https://github.com/geneseas/ksuid-python.git
Project-URL: Bug Reports, https://github.com/geneseas/ksuid-python/issues
Project-URL: Changelog, https://github.com/geneseas/ksuid-python/blob/main/CHANGELOG.md
Author-email: Tototheo Development Team <anton.z@tototheo.com>
Maintainer-email: Tototheo Development Team <anton.z@tototheo.com>
License: MIT License
License-File: LICENSE
Keywords: id,identifier,ksuid,sortable,timestamp,unique,uuid
Classifier: Development Status :: 5 - Production/Stable
Classifier: Intended Audience :: Developers
Classifier: License :: OSI Approved :: MIT License
Classifier: Operating System :: OS Independent
Classifier: Programming Language :: Python :: 3
Classifier: Programming Language :: Python :: 3 :: Only
Classifier: Programming Language :: Python :: 3.13
Classifier: Topic :: Database
Classifier: Topic :: Software Development :: Libraries :: Python Modules
Classifier: Topic :: System :: Distributed Computing
Classifier: Topic :: Utilities
Requires-Python: >=3.13
Provides-Extra: dev
Requires-Dist: black>=21.0; extra == 'dev'
Requires-Dist: flake8>=3.8; extra == 'dev'
Requires-Dist: isort>=5.0; extra == 'dev'
Requires-Dist: mypy>=0.910; extra == 'dev'
Requires-Dist: pre-commit>=2.15.0; extra == 'dev'
Requires-Dist: pytest-benchmark>=3.4.0; extra == 'dev'
Requires-Dist: pytest-cov>=2.0; extra == 'dev'
Requires-Dist: pytest>=6.0; extra == 'dev'
Provides-Extra: test
Requires-Dist: pytest-benchmark>=3.4.0; extra == 'test'
Requires-Dist: pytest-cov>=2.0; extra == 'test'
Requires-Dist: pytest>=6.0; extra == 'test'
